sees/__init__.py
sees/__main__.py
sees/config.py
sees/errors.py
sees/fibers.py
sees/model.py
sees/parser.py
sees/section.py
sees/server.py
sees/state.py
sees/tcl.py
sees/archive/_render.py
sees/assets/chrystals_moment.stl
sees/assets/pointer_arrows.glb
sees/canvas/canvas.py
sees/canvas/gltf.py
sees/canvas/mpl.py
sees/canvas/ply.py
sees/canvas/tri.py
sees/canvas/femgl/__init__.py
sees/canvas/femgl/convert/convert.py
sees/canvas/femgl/convert/example.py
sees/frame/__init__.py
sees/frame/extrude.py
sees/plane/__init__.py
sees/reader/__main__.py
sees/reader/csi.py
sees/utility/__init__.py
sees/utility/alpha_shape.py
sees/utility/consolidate.py
sees/viewer/__init__.py
sees/viewer/__main__.py
sees-0.0.24.dist-info/METADATA
sees-0.0.24.dist-info/WHEEL
sees-0.0.24.dist-info/entry_points.txt
sees-0.0.24.dist-info/top_level.txt
sees-0.0.24.dist-info/RECORD
