Metadata-Version: 2.1
Name: sees
Version: 0.0.24
Summary: Nonlinear finite element analysis
Author-email: "Claudio M. Perez" <50180406+claudioperez@users.noreply.github.com>, Chrystal Chern <52893467+chrystalchern@users.noreply.github.com>
Project-URL: Repository, https://github.com/STAIRLab/sees
Project-URL: Documentation, https://stairlab.github.io/opensees-gallery
Keywords: visualization,rendering,seismic,opensees,nonlinear,post-processing,finite-element-analysis,glTF
Classifier: Development Status :: 4 - Beta
Classifier: Intended Audience :: Science/Research
Classifier: Intended Audience :: Developers
Classifier: License :: OSI Approved :: BSD License
Classifier: Programming Language :: C
Classifier: Programming Language :: Python
Classifier: Programming Language :: Python :: 3
Classifier: Programming Language :: Python :: 3.7
Classifier: Programming Language :: Python :: 3.8
Classifier: Programming Language :: Python :: 3.9
Classifier: Programming Language :: Python :: 3.10
Classifier: Programming Language :: Python :: 3.11
Classifier: Programming Language :: Python :: 3.12
Classifier: Programming Language :: Python :: 3 :: Only
Classifier: Topic :: Software Development
Classifier: Topic :: Scientific/Engineering
Classifier: Operating System :: Microsoft :: Windows
Classifier: Operating System :: POSIX
Classifier: Operating System :: Unix
Classifier: Operating System :: MacOS
Requires-Dist: opensees
Requires-Dist: quakeio
Requires-Dist: bottle
Requires-Dist: openbim
Requires-Dist: pyyaml
Requires-Dist: scipy
Requires-Dist: numpy
Requires-Dist: plotly
Requires-Dist: pygltflib
Requires-Dist: matplotlib
Requires-Dist: shps
